tfbench/__init__.py
tfbench/add_dependency.py
tfbench/common.py
tfbench/dataset.py
tfbench/env.py
tfbench/error_analysis.py
tfbench/evaluation.py
tfbench/experiment.py
tfbench/ghc.py
tfbench/hoogle.py
tfbench/hs_parser/__init__.py
tfbench/hs_parser/ast_util.py
tfbench/hs_parser/extractor.py
tfbench/hs_parser/type_util.py
tfbench/lm/__init__.py
tfbench/lm/_anthropic.py
tfbench/lm/_google.py
tfbench/lm/_hf.py
tfbench/lm/_ollama.py
tfbench/lm/_openai.py
tfbench/lm/_types.py
tfbench/lm/prompts.py
tfbench/lm/settings.py
tfbench/lm/utils.py
tfbench/load.py
tfbench/manual.py
tfbench/postprocessing.py
tfbench/prelude.py
tfbench/type_def.py
tfbench-1.0.0.dist-info/WHEEL
tfbench-1.0.0.dist-info/METADATA
tfbench-1.0.0.dist-info/RECORD
