Metadata-Version: 2.3
Name: tfbench
Version: 1.0.0
Summary: Evaluating Program Semantics Reasoning with Type Inference in System F
Requires-Dist: anthropic==0.49.0
Requires-Dist: dacite>=1.8.1
Requires-Dist: datasets>=4.0.0
Requires-Dist: deprecated>=1.2.18
Requires-Dist: dotenv>=0.9.9
Requires-Dist: fire==0.5.0
Requires-Dist: funcy==2.0
Requires-Dist: funcy-chain==0.2.0
Requires-Dist: google-genai==1.31.0
Requires-Dist: hypothesis>=6.98.6
Requires-Dist: markdown-to-json==2.1.2
Requires-Dist: matplotlib>=3.8.3
Requires-Dist: numpy>=1.26.4
Requires-Dist: ollama==0.5.3
Requires-Dist: openai==1.99.9
Requires-Dist: orjson>=3.11.3
Requires-Dist: orjsonl>=1.0.0
Requires-Dist: pokepalette>=0.0.6
Requires-Dist: pyarrow>=21.0.0
Requires-Dist: pydantic>=2.11.7
Requires-Dist: pytest>=8.0.0
Requires-Dist: python-dotenv==1.0.1
Requires-Dist: requests==2.32.3
Requires-Dist: returns[compatible-mypy]>=0.26.0
Requires-Dist: seaborn==0.13.2
Requires-Dist: tabulate>=0.9.0
Requires-Dist: tenacity>=9.1.2
Requires-Dist: tiktoken==0.7.0
Requires-Dist: tqdm>=4.66.2
Requires-Dist: transformers[torch]>=4.55.4
Requires-Dist: tree-sitter==0.22.3
Requires-Dist: tree-sitter-haskell==0.21.0
Requires-Dist: types-deprecated>=1.2.15.20250304
Requires-Dist: types-requests>=2.31.0
Requires-Python: >=3.12
